staby/__init__.py
staby/admin/__init__.py
staby/admin/apps.py
staby/admin/lazy_admin.py
staby/articles/__init__.py
staby/articles/admin.py
staby/articles/apps.py
staby/articles/models.py
staby/articles/tests.py
staby/articles/urls.py
staby/articles/views.py
staby/articles/migrations/0001_initial.py
staby/articles/migrations/0002_auto_20200506_0835.py
staby/articles/migrations/__init__.py
staby/blog/__init__.py
staby/blog/admin.py
staby/blog/apps.py
staby/blog/models.py
staby/blog/tests.py
staby/blog/urls.py
staby/blog/views.py
staby/blog/migrations/0001_initial.py
staby/blog/migrations/__init__.py
staby/core/__init__.py
staby/core/admin.py
staby/core/apps.py
staby/core/context_processors.py
staby/core/fields.py
staby/core/forms.py
staby/core/models.py
staby/core/tests.py
staby/core/urls.py
staby/core/views.py
staby/core/widgets.py
staby/core/static/staby/js/jquery-3.4.1.min.js
staby/core/static/staby/js/tiny_mce.setup.js
staby/core/static/staby/js/tinymce/jquery.tinymce.min.js
staby/core/static/staby/js/tinymce/license.txt
staby/core/static/staby/js/tinymce/tinymce.min.js
staby/core/static/staby/js/tinymce/langs/readme.md
staby/core/static/staby/js/tinymce/plugins/advlist/plugin.min.js
staby/core/static/staby/js/tinymce/plugins/anchor/plugin.min.js
staby/core/static/staby/js/tinymce/plugins/autolink/plugin.min.js
staby/core/static/staby/js/tinymce/plugins/autoresize/plugin.min.js
staby/core/static/staby/js/tinymce/plugins/autosave/plugin.min.js
staby/core/static/staby/js/tinymce/plugins/bbcode/plugin.min.js
staby/core/static/staby/js/tinymce/plugins/charmap/plugin.min.js
staby/core/static/staby/js/tinymce/plugins/code/plugin.min.js
staby/core/static/staby/js/tinymce/plugins/codesample/plugin.min.js
staby/core/static/staby/js/tinymce/plugins/colorpicker/plugin.min.js
staby/core/static/staby/js/tinymce/plugins/contextmenu/plugin.min.js
staby/core/static/staby/js/tinymce/plugins/directionality/plugin.min.js
staby-0.1.6.dist-info/LICENSE
staby-0.1.6.dist-info/METADATA
staby-0.1.6.dist-info/WHEEL
staby-0.1.6.dist-info/top_level.txt
staby-0.1.6.dist-info/RECORD
